jd_excel/__init__.py
jd_excel/main.py
jd_excel/utils.py
jd_jinghui_excel_mcp-0.2.3.dist-info/METADATA
jd_jinghui_excel_mcp-0.2.3.dist-info/WHEEL
jd_jinghui_excel_mcp-0.2.3.dist-info/entry_points.txt
jd_jinghui_excel_mcp-0.2.3.dist-info/RECORD
