Metadata-Version: 2.4
Name: jd-jinghui-excel-mcp
Version: 0.2.3
Summary: My powerful Excel MCP tool
Requires-Dist: fastmcp
Requires-Dist: openpyxl
Requires-Dist: pandas
